caveble.py
circuitpython_caveble-1.1.2.dist-info/LICENSE
circuitpython_caveble-1.1.2.dist-info/METADATA
circuitpython_caveble-1.1.2.dist-info/WHEEL
circuitpython_caveble-1.1.2.dist-info/top_level.txt
circuitpython_caveble-1.1.2.dist-info/RECORD
