Metadata-Version: 2.1
Name: circuitpython-caveble
Version: 1.1.2
Summary: Cave Surveying Bluetooth Protocol
Author-email: Phil Underwood <beardydoc@gmail.com>
License: MIT
Project-URL: Homepage, https://github.com/furbrain/CircuitPython_CaveBLE
Keywords: adafruit,blinka,circuitpython,micropython,disto,distox,bluetooth,cave,survey,caveble
Classifier: Intended Audience :: Developers
Classifier: Topic :: Software Development :: Libraries
Classifier: Topic :: Software Development :: Embedded Systems
Classifier: Topic :: System :: Hardware
Classifier: License :: OSI Approved :: MIT License
Classifier: Programming Language :: Python :: 3
License-File: LICENSE
Requires-Dist: Adafruit-Blinka
Requires-Dist: adafruit-circuitpython-ble
Provides-Extra: optional
Requires-Dist: adafruit-circuitpython-asyncio ; extra == 'optional'
